LICENSE.BAYKIT
README.md
setup.py
bayserver_docker_cgi/__init__.py
bayserver_docker_cgi/cgi_docker.py
bayserver_docker_cgi/cgi_message.py
bayserver_docker_cgi/cgi_req_content_handler.py
bayserver_docker_cgi/cgi_std_err_ship.py
bayserver_docker_cgi/cgi_std_out_ship.py
bayserver_docker_cgi/cgi_symbol.py
bayserver_docker_cgi/cgi_train.py
bayserver_docker_cgi/php_cgi_docker.py
bayserver_docker_cgi.egg-info/PKG-INFO
bayserver_docker_cgi.egg-info/SOURCES.txt
bayserver_docker_cgi.egg-info/dependency_links.txt
bayserver_docker_cgi.egg-info/requires.txt
bayserver_docker_cgi.egg-info/top_level.txt