Metadata-Version: 1.2
Name: bayserver-docker-cgi
Version: 3.0.0
Summary: CGI Docker for BayServer
Home-page: https://baykit.yokohama/
Author: Michisuke-P
Author-email: michisukep@gmail.com
License: MIT
Platform: UNKNOWN
Requires-Python: >=3.7
